cacheman/__init__.py
cacheman/autosync.py
cacheman/cacher.py
cacheman/cacheutils.py
cacheman/cachewrap.py
cacheman/csvcache.py
cacheman/registers.py
cacheman/utils.py
CacheMan-2.2.0.dist-info/LICENSE
CacheMan-2.2.0.dist-info/METADATA
CacheMan-2.2.0.dist-info/WHEEL
CacheMan-2.2.0.dist-info/top_level.txt
CacheMan-2.2.0.dist-info/RECORD
