Metadata-Version: 2.1
Name: CacheMan
Version: 2.2.0
Summary: A dependent cache manager
Home-page: https://github.com/MSeal/py_cache_manager
Download-URL: https://github.com/MSeal/py_cache_manager/tarball/v2.2.0
Author: Matthew Seal
Author-email: mseal007@gmail.com
License: New BSD
Keywords: tables,data,analysis,extraction
Classifier: Development Status :: 4 - Beta
Classifier: Topic :: Utilities
Classifier: License :: OSI Approved :: BSD License
Classifier: Natural Language :: English
Classifier: Programming Language :: Python :: 3
License-File: LICENSE
Requires-Dist: psutil (>=2.1.0)
